{
  "__comment": "Generated by generateResources.py function: blockstate",
  "forge_marker": 1,
  "variants": {
    "normal": [
            { "model": "contenttweaker:ore/quartz/dolomite" },
            { "model": "contenttweaker:ore/quartz/dolomite", "x": 90 },
            { "model": "contenttweaker:ore/quartz/dolomite", "x": 180 },
            { "model": "contenttweaker:ore/quartz/dolomite", "x": 270 },
            { "model": "contenttweaker:ore/quartz/dolomite", "y": 90 },
            { "model": "contenttweaker:ore/quartz/dolomite", "y": 90, "x": 90 },
            { "model": "contenttweaker:ore/quartz/dolomite", "y": 90, "x": 180 },
            { "model": "contenttweaker:ore/quartz/dolomite", "y": 90, "x": 270 },
            { "model": "contenttweaker:ore/quartz/dolomite", "y": 180 },
            { "model": "contenttweaker:ore/quartz/dolomite", "y": 180, "x": 90 },
            { "model": "contenttweaker:ore/quartz/dolomite", "y": 180, "x": 180 },
            { "model": "contenttweaker:ore/quartz/dolomite", "y": 180, "x": 270 },
            { "model": "contenttweaker:ore/quartz/dolomite", "y": 270 },
            { "model": "contenttweaker:ore/quartz/dolomite", "y": 270, "x": 90 },
            { "model": "contenttweaker:ore/quartz/dolomite", "y": 270, "x": 180 },
            { "model": "contenttweaker:ore/quartz/dolomite", "y": 270, "x": 270 }
    ]
  }
}